README.md
configuration.py
setup.cfg
setup.py
streamlink_helper.py
util.py
streamlink_helper.egg-info/PKG-INFO
streamlink_helper.egg-info/SOURCES.txt
streamlink_helper.egg-info/dependency_links.txt
streamlink_helper.egg-info/entry_points.txt
streamlink_helper.egg-info/requires.txt
streamlink_helper.egg-info/top_level.txt