Metadata-Version: 1.1
Name: streamlink-helper
Version: 0.6
Summary: Just a little helper script for Streamlink
Home-page: https://github.com/cronos23/streamlink_helper
Author: Ossi Kronlöf
Author-email: ossikronlof@gmail.com
License: UNKNOWN
Download-URL: https://github.com/cronos23/streamlink_helper/archive/0.6.tar.gz
Platform: UNKNOWN
